cancer_researcher_ai/Final_Stacked_Data_without_Duplicates.csv
cancer_researcher_ai/__init__.py
cancer_researcher_ai/main.py
cancer_researcher_ai-0.2.1.dist-info/METADATA
cancer_researcher_ai-0.2.1.dist-info/WHEEL
cancer_researcher_ai-0.2.1.dist-info/entry_points.txt
cancer_researcher_ai-0.2.1.dist-info/top_level.txt
cancer_researcher_ai-0.2.1.dist-info/RECORD
